feats/__init__.py
feats/feats_batchcorrection.py
feats/feats_clustering.py
feats/feats_detectoutliers.py
feats/feats_filtering.py
feats/feats_gapstatistics.py
feats/feats_transformations.py
feats/feats_utils.py
feats-1.0.1.dist-info/LICENSE
feats-1.0.1.dist-info/METADATA
feats-1.0.1.dist-info/WHEEL
feats-1.0.1.dist-info/top_level.txt
feats-1.0.1.dist-info/RECORD
