Metadata-Version: 2.1
Name: feats
Version: 1.0.1
Summary: A Python tool for performing downstream analysis on Single Cell RNA-seq datasets
Home-page: https://github.com/edwinv87/feats
Author: Edwin Vans
Author-email: vans.edw@gmail.com
License: UNKNOWN
Platform: UNKNOWN
Classifier: Programming Language :: Python :: 3
Classifier: License :: OSI Approved :: MIT License
Classifier: Operating System :: OS Independent
Requires-Python: >=3.6
